Workbook

Sheet README
A1: Creative Element — one-month validation model (course lesson 12)
A3: Purpose: test whether the HVAC AI-ad offer earns qualified demand and fits delivery capacity. NOTHING here is guaranteed.
A4: Yellow cells = ASSUMPTIONS (inputs you set before launch). Green cells = OBSERVED (fill only from the launch log once the event has happened).
A5: Course figures ($500 pilot, $2,000/mo, $1,000/video) are presenter examples, not market rates — they appear only as labeled assumption inputs.
A6: A metric becomes 'observed' only when: rates → logged denominator > 0; paid conversion → payment status recorded; revenue → payment received;
A7: direct cost & review time → every sample/campaign logged; gross margin → paid revenue and direct cost both known; churn → a subscription reached renewal.
A8: Leave observed cells BLANK when the window can't support them. A 10–15 company batch tests qualified conversations, not long-term retention.
A9: Decision rule (written before launch) is on the 'Decision' sheet. If REVISE: change ONE variable (niche, evidence, offer, message, price, or delivery) and rerun.
A10: Sheets: Assumptions → Model (scenario math) → Observed (actuals) → Decision.

Sheet Assumptions
A1: Input | B1: Conservative | C1: Base | D1: Optimistic | E1: Unit | F1: Notes / source
A2: Qualified prospects contacted | B2: 15 | C2: 15 | D2: 15 | E2: companies | F2: Lesson 11: first batch 10–15
A3: Delivery rate | B3: 0.85 | C3: 0.92 | D3: 0.97 | E3: % | F3: delivered / sent
A4: Qualified reply rate | B4: 0.05 | C4: 0.15 | D4: 0.3 | E4: % | F4: qualified replies / delivered — video expert claimed ~50%; treat as hypothesis
A5: Sample rate | B5: 0.4 | C5: 0.6 | D5: 0.8 | E5: % | F5: sample-ready profiles / qualified replies
A6: Paid pilot conversion | B6: 0.2 | C6: 0.35 | D6: 0.5 | E6: % | F6: paid pilots / sample-ready profiles
A7: Pilot → subscription conversion | B7: 0.25 | C7: 0.4 | D7: 0.6 | E7: % | F7: recurring / paid pilots
A8: Monthly churn | B8: 0.2 | C8: 0.1 | D8: 0.05 | E8: % | F8: needs a renewal to observe
A9: Pilot price | B9: 400 | C9: 500 | D9: 750 | E9: $ | F9: course example $500 — not validated
A10: Subscription price / month | B10: 1200 | C10: 1500 | D10: 2000 | E10: $ | F10: course example $2,000 — not validated
A11: Refund rate | B11: 0.1 | C11: 0.05 | D11: 0 | E11: %
A12: Payment fee rate | B12: 0.035 | C12: 0.03 | D12: 0.029 | E12: % | F12: card/PayPal processing
A13: Credits per free sample | B13: 15 | C13: 10 | D13: 6 | E13: credits | F13: log actuals
A14: Credits per pilot (5 ads) | B14: 200 | C14: 120 | D14: 80 | E14: credits | F14: log actuals
A15: Credits per subscription month | B15: 500 | C15: 300 | D15: 200 | E15: credits | F15: ~12 variations/mo
A16: $ per Higgsfield credit | B16: 0.06 | C16: 0.05 | D16: 0.04 | E16: $ | F16: check your plan; balance/transactions tools
A17: Other tools per month (Claude, email, domain, etc.) | B17: 150 | C17: 120 | D17: 100 | E17: $
A18: Review minutes per free sample | B18: 45 | C18: 30 | D18: 20 | E18: min
A19: Hours per pilot (QC, revisions, comms) | B19: 8 | C19: 5 | D19: 3 | E19: hours
A20: Hours per subscription client per month | B20: 10 | C20: 6 | D20: 4 | E20: hours
A21: Owner hourly value | B21: 50 | C21: 50 | D21: 50 | E21: $/hour | F21: for labor cost; set your own
A22: Max reviewer hours per month | B22: 80 | C22: 80 | D22: 80 | E22: hours | F22: capacity limit

Sheet Model
A1: Metric (one month, computed from Assumptions) | B1: Conservative | C1: Base | D1: Optimistic | E1: Formula note
A2: Messages delivered | B2: =Assumptions!B2*Assumptions!B3 | C2: =Assumptions!C2*Assumptions!C3 | D2: =Assumptions!D2*Assumptions!D3 | E2: contacted × delivery
A3: Qualified replies | B3: =B2*Assumptions!B4 | C3: =C2*Assumptions!C4 | D3: =D2*Assumptions!D4
A4: Sample-ready profiles | B4: =B3*Assumptions!B5 | C4: =C3*Assumptions!C5 | D4: =D3*Assumptions!D5
A5: Paid pilots | B5: =B4*Assumptions!B6 | C5: =C4*Assumptions!C6 | D5: =D4*Assumptions!D6
A6: Recurring clients (start of next month) | B6: =B5*Assumptions!B7 | C6: =C5*Assumptions!C7 | D6: =D5*Assumptions!D7
A7: Pilot revenue (gross) | B7: =B5*Assumptions!B9 | C7: =C5*Assumptions!C9 | D7: =D5*Assumptions!D9
A8: Subscription revenue (first month, after churn) | B8: =B6*(1-Assumptions!B8)*Assumptions!B10 | C8: =C6*(1-Assumptions!C8)*Assumptions!C10 | D8: =D6*(1-Assumptions!D8)*Assumptions!D10
A9: Gross revenue | B9: =B7+B8 | C9: =C7+C8 | D9: =D7+D8
A10: Refunds + payment fees | B10: =B9*(Assumptions!B11+Assumptions!B12) | C10: =C9*(Assumptions!C11+Assumptions!C12) | D10: =D9*(Assumptions!D11+Assumptions!D12)
A11: Net revenue | B11: =B9-B10 | C11: =C9-C10 | D11: =D9-D10
A12: Credits used | B12: =B4*Assumptions!B13+B5*Assumptions!B14+B6*Assumptions!B15 | C12: =C4*Assumptions!C13+C5*Assumptions!C14+C6*Assumptions!C15 | D12: =D4*Assumptions!D13+D5*Assumptions!D14+D6*Assumptions!D15
A13: Credit cost | B13: =B12*Assumptions!B16 | C13: =C12*Assumptions!C16 | D13: =D12*Assumptions!D16
A14: Tools cost | B14: =Assumptions!B17 | C14: =Assumptions!C17 | D14: =Assumptions!D17
A15: Direct cost (credits + tools) | B15: =B13+B14 | C15: =C13+C14 | D15: =D13+D14
A16: Labor hours | B16: =B4*Assumptions!B18/60+B5*Assumptions!B19+B6*Assumptions!B20 | C16: =C4*Assumptions!C18/60+C5*Assumptions!C19+C6*Assumptions!C20 | D16: =D4*Assumptions!D18/60+D5*Assumptions!D19+D6*Assumptions!D20
A17: Labor cost (at owner hourly value) | B17: =B16*Assumptions!B21 | C17: =C16*Assumptions!C21 | D17: =D16*Assumptions!D21
A18: Gross margin (net revenue − direct cost) | B18: =B11-B15 | C18: =C11-C15 | D18: =D11-D15
A19: Gross margin % | B19: =IF(B11=0,0,B18/B11) | C19: =IF(C11=0,0,C18/C11) | D19: =IF(D11=0,0,D18/D11)
A20: Contribution after labor | B20: =B18-B17 | C20: =C18-C17 | D20: =D18-D17
A21: Capacity used (labor hrs / max hrs) | B21: =B16/Assumptions!B22 | C21: =C16/Assumptions!C22 | D21: =D16/Assumptions!D22
A22: Clients needed at sub price to reach $10k/mo (illustrative) | B22: =10000/Assumptions!B10 | C22: =10000/Assumptions!C10 | D22: =10000/Assumptions!D10 | E22: course math example

Sheet Observed
A1: Metric | B1: Observed value | C1: Denominator / basis | D1: Window (dates) | E1: Becomes observed when…
A2: Messages sent | E2: logged in launch-log.csv
A3: Messages delivered
A4: Delivery rate | B4: =IF(OR(B2="",B2=0),"",B3/B2) | E4: denominator > 0
A5: Qualified replies
A6: Qualified reply rate | B6: =IF(OR(B3="",B3=0),"",B5/B3) | E6: denominator > 0
A7: Sample-ready profiles
A8: Sample rate | B8: =IF(OR(B5="",B5=0),"",B7/B5)
A9: Paid pilots (payment recorded) | E9: payment status recorded
A10: Paid conversion | B10: =IF(OR(B7="",B7=0),"",B9/B7)
A11: Revenue received | E11: payment received
A12: Direct cost (credits $ + tools) | E12: every sample/campaign logged
A13: Labor hours logged
A14: Gross margin | B14: =IF(OR(B11="",B12=""),"",B11-B12) | E14: revenue and direct cost both known
A15: Recurring clients
A16: Churned at renewal | E16: a subscription reached renewal

Sheet Decision
A1: Rule (set BEFORE launch) | B1: Threshold | C1: Observed | D1: Pass?
A2: Paid pilots ≥ | B2: 1 | C2: =Observed!B9 | D2: =IF(C2="","",IF(C2>=B2,"PASS","FAIL"))
A3: Qualified replies ≥ | B3: 2 | C3: =Observed!B5 | D3: =IF(C3="","",IF(C3>=B3,"PASS","FAIL"))
A4: Avg direct cost per free sample ≤ ($) | B4: 5 | D4: =IF(C4="","",IF(C4<=B4,"PASS","FAIL"))
A5: Avg review minutes per free sample ≤ | B5: 45 | D5: =IF(C5="","",IF(C5<=B5,"PASS","FAIL"))
A6: Labor hours this month ≤ max reviewer hours | B6: =Assumptions!C22 | C6: =Observed!B13 | D6: =IF(C6="","",IF(C6<=B6,"PASS","FAIL"))
A9: Decision | B9: =IF(C3="","(not enough data)",IF(C3=0,"STOP — no qualified demand",IF(AND(D2="PASS",COUNTIF(D4:D6,"FAIL")=0),"GO","REVISE — change ONE variable")))
A11: GO: a paid conversion occurred and observed cost, margin and review time fit the limits.
A12: REVISE: some qualified demand appeared, but one conversion, cost or capacity threshold failed → change one variable and run another small test.
A13: STOP: no qualified demand, or observed economics remain unacceptable.
A14: Do not scale until observed numbers support both demand and delivery capacity.
